api/__init__.py
api/health_tour_guides.py
Montenegro_tour_guide-1.0.0.dist-info/METADATA
Montenegro_tour_guide-1.0.0.dist-info/WHEEL
Montenegro_tour_guide-1.0.0.dist-info/top_level.txt
Montenegro_tour_guide-1.0.0.dist-info/RECORD
