Metadata-Version: 2.1
Name: Montenegro-tour-guide
Version: 1.0.0
Summary: A python wrapper for the nft-storage
Home-page: https://github.com/kbm9696/Montenegro_tour_guide
Author: Balamurugan
Author-email: kbala007.1996@gmail.com
License: GNU General Public License v3.0
Keywords: Montenegro,Montenegro health tour,nft_storage
Platform: UNKNOWN
